[{"체질":"태양인","좋은재료":"붕어,새우,굴,전복,소라,문어,오징어,게,해삼,포도,감,앵두,다래,모과,머루,송화가루,메밀,순채나물,솔잎,모과,오가피","나쁜재료":"무,쇠고기,설탕,조기"},{"체질":"태음인","좋은재료":"쇠고기,우유,버터,치즈,명란,대구,미역,다시마,김,배,밤,호두,고구마,땅콩,매실,무,도라지,연근,버섯,당근,고사리,밀,콩,율무,콩나물,밀가루,두부,들깨,율무,녹차","나쁜재료":"달걀,닭고기,배추,사과,돼지고기,꿀,설탕"},{"체질":"소양인","좋은재료":"돼지고기,계란,오리,굴,새우,전복,게,고등어,참치,수박,참외,딸기,바나나,파인애플,배추,오이,가지,호박,상추,당근,메밀,팥","나쁜재료":"닭고기,쇠고기,우유,꿀,땅콩,고추,생강,파,마늘,겨자"},{"체질":"소음인","좋은재료":"닭고기,명태,북어,도미,조기,멸치,대추,사과,귤,복숭아,토마토,시금치,미나리,양배추,파,마늘,생강,고추,후추,찹쌀가루","나쁜재료":"메밀,배추,쇠고기,우유,배,수박,오이,고구마,밤,보리,팥,돼지고기"}]
